setup.py
hash/__init__.py
hash/package.py
hashsystem_token.egg-info/PKG-INFO
hashsystem_token.egg-info/SOURCES.txt
hashsystem_token.egg-info/dependency_links.txt
hashsystem_token.egg-info/top_level.txt